README.txt
setup.py
collective/__init__.py
collective.projekktor.egg-info/PKG-INFO
collective.projekktor.egg-info/SOURCES.txt
collective.projekktor.egg-info/dependency_links.txt
collective.projekktor.egg-info/entry_points.txt
collective.projekktor.egg-info/namespace_packages.txt
collective.projekktor.egg-info/not-zip-safe
collective.projekktor.egg-info/requires.txt
collective.projekktor.egg-info/top_level.txt
collective/projekktor/__init__.py
collective/projekktor/compilepo
collective/projekktor/configure.zcml
collective/projekktor/exportimport.py
collective/projekktor/interfaces.py
collective/projekktor/projekktor.py
collective/projekktor/provider.py
collective/projekktor/tests.py
collective/projekktor/utility.py
collective/projekktor/browser/__init__.py
collective/projekktor/browser/configure.zcml
collective/projekktor/browser/interfaces.py
collective/projekktor/browser/controls/__init__.py
collective/projekktor/browser/controls/configure.zcml
collective/projekktor/browser/controls/projekktor_controls.py
collective/projekktor/browser/portlets/__init__.py
collective/projekktor/browser/portlets/configure.zcml
collective/projekktor/browser/portlets/projekktor_portlet.pt
collective/projekktor/browser/portlets/projekktor_portlet.py
collective/projekktor/browser/viewlets/__init__.py
collective/projekktor/browser/viewlets/configure.zcml
collective/projekktor/browser/viewlets/player.pt
collective/projekktor/browser/viewlets/projekktor_viewlet.py
collective/projekktor/browser/views/__init__.py
collective/projekktor/browser/views/configure.zcml
collective/projekktor/browser/views/projekktor_view.pt
collective/projekktor/browser/views/projekktor_view.py
collective/projekktor/doctests/adapter_media.txt
collective/projekktor/doctests/adapter_portlet_provider.txt
collective/projekktor/doctests/adapter_view_provider.txt
collective/projekktor/doctests/browser_controls.txt
collective/projekktor/doctests/browser_portlets.txt
collective/projekktor/doctests/browser_views.txt
collective/projekktor/doctests/exportimport.txt
collective/projekktor/doctests/projekktor.mp3
collective/projekktor/doctests/projekktor.mp4
collective/projekktor/doctests/projekktor.ogg
collective/projekktor/doctests/projekktor.ogv
collective/projekktor/doctests/projekktor.png
collective/projekktor/doctests/utility.txt
collective/projekktor/locales/collective.projekktor.pot
