Metadata-Version: 1.0
Name: collective.projekktor
Version: 0.2b1
Summary: Ploneised version of Projekktor html5 media player.
Home-page: http://packages.python.org/collective.projekktor
Author: Ryan Northey, Paul Hennell
Author-email: code@3ca.org.uk
License: GPL
Download-URL: http://pypi.python.org/pypi/collective.projekktor/
Keywords: html5 fallback flash video audio media widget
Platform: UNKNOWN
Classifier: Programming Language :: Python
